warehut/__init__.py
warehut/consumer.py
warehut/hybrid.py
warehut/packet.py
warehut/producer.py
warehut/warehut.py
warehut/worker.py
warehut-3.4.0.dist-info/LICENSE
warehut-3.4.0.dist-info/WHEEL
warehut-3.4.0.dist-info/METADATA
warehut-3.4.0.dist-info/RECORD
