Metadata-Version: 2.1
Name: warehut
Version: 3.4.0
Summary: Manage producer and consumer workers
Home-page: https://gitlab.com/deepadmax/warehut
License: GPL-3.0-or-later
Author: Maximillian Strand
Author-email: maximillian.strand@protonmail.com
Requires-Python: >=3.9,<4.0
Classifier: License :: OSI Approved :: GNU General Public License v3 or later (GPLv3+)
Classifier: Programming Language :: Python :: 3
Classifier: Programming Language :: Python :: 3.10
Classifier: Programming Language :: Python :: 3.9
